python_rest_handler
tests
