Metadata-Version: 1.1
Name: python-rest-handler
Version: 0.0.2
Summary: A simple and abstract library to create Read Handlers for different Web frameworks and ORMs.
Home-page: https://github.com/paulocheque/python-rest-handler
Author: paulocheque
Author-email: paulocheque@gmail.com
License: MIT
Keywords: python requests rest handlers
Platform: UNKNOWN
Classifier: Operating System :: OS Independent
Classifier: Topic :: Software Development
